coreason_graph_nexus/__init__.py
coreason_graph_nexus/adapters/__init__.py
coreason_graph_nexus/adapters/neo4j_adapter.py
coreason_graph_nexus/adapters/parquet_adapter.py
coreason_graph_nexus/compute.py
coreason_graph_nexus/config.py
coreason_graph_nexus/interfaces.py
coreason_graph_nexus/link_prediction.py
coreason_graph_nexus/main.py
coreason_graph_nexus/models.py
coreason_graph_nexus/ontology.py
coreason_graph_nexus/projector.py
coreason_graph_nexus/server.py
coreason_graph_nexus/service.py
coreason_graph_nexus/utils/__init__.py
coreason_graph_nexus/utils/batching.py
coreason_graph_nexus/utils/logger.py
coreason_graph_nexus-0.4.0.dist-info/METADATA
coreason_graph_nexus-0.4.0.dist-info/WHEEL
coreason_graph_nexus-0.4.0.dist-info/licenses/LICENSE
coreason_graph_nexus-0.4.0.dist-info/licenses/NOTICE
coreason_graph_nexus-0.4.0.dist-info/RECORD
