Metadata-Version: 2.4
Name: coreason_graph_nexus
Version: 0.4.0
Summary: orchestration engine for knowledge graph
License: # The Prosperity Public License 3.0.0
License-File: LICENSE
License-File: NOTICE
Author: Gowtham A Rao
Author-email: gowtham.rao@coreason.ai
Requires-Python: >=3.11
Classifier: License :: Other/Proprietary License
Classifier: Programming Language :: Python :: 3.12
Classifier: Operating System :: OS Independent
Requires-Dist: aiofiles (>=25.1.0,<26.0.0)
Requires-Dist: anyio (>=4.12.1,<5.0.0)
Requires-Dist: fastapi (>=0.115.0,<0.116.0)
Requires-Dist: httpx (>=0.28.1,<0.29.0)
Requires-Dist: loguru (>=0.7.2,<0.8.0)
Requires-Dist: neo4j (>=6.1.0,<7.0.0)
Requires-Dist: networkx (>=3.6.1,<4.0.0)
Requires-Dist: numpy (>=2.4.1,<3.0.0)
Requires-Dist: pyarrow (>=23.0.0,<24.0.0)
Requires-Dist: pydantic (>=2.12.5,<3.0.0)
Requires-Dist: pydantic-settings (>=2.12.0,<3.0.0)
Requires-Dist: pyyaml (>=6.0.3,<7.0.0)
Requires-Dist: redis[hiredis] (>=7.1.0,<8.0.0)
Requires-Dist: scikit-learn (>=1.8.0,<2.0.0)
Requires-Dist: scipy (>=1.17.0,<2.0.0)
Requires-Dist: uvicorn (>=0.30.0,<0.31.0)
Project-URL: Documentation, https://github.com/CoReason-AI/coreason_graph_nexus
Project-URL: Homepage, https://github.com/CoReason-AI/coreason_graph_nexus
Project-URL: Repository, https://github.com/CoReason-AI/coreason_graph_nexus
